{
  "description": "Applicazione per email multipiattaforma con supporto alla cifratura tramite il componente aggiuntivo Enigmail.",
  "license_url": "https://www.mozilla.org/MPL/",
  "logo": "mozilla-thunderbird.png",
  "notes": "Thunderbird non cifra le email in modo predefinito. [Qui si trova una guida](https://securityinabox.org/en/thunderbird_main) di Security In A Box per cifrare le tue email con Mozilla Thunderbird, GNU Privacy Guard (GPG) ed Enigmail.\n\nThunderbird pu&ograve; anche connettersi a Tor con l&#39;addon TorBirdy.\n\nSebbene Thunderbird possa essere usato anche come client di chat e IRC, non permette la cifratura dei messaggi.",
  "privacy_url": "https://www.mozilla.org/en-US/privacy/policies/websites/",
  "source_url": "https://developer.mozilla.org/it/docs/Viewing_and_searching_Mozilla_source_code_online",
  "name": "Mozilla Thunderbird",
  "tos_url": "https://www.mozilla.org/en-US/about/legal.html",
  "url": "https://www.mozilla.org/it/thunderbird/",
  "wikipedia_url": "https://it.wikipedia.org/wiki/Mozilla_Thunderbird",
  "protocols": [
    "GPG",
    "IRC",
    "RSS",
    "S/MIME",
    "SSL/TLS",
    "Tor",
    "XMPP"
  ],
  "categories": [
    {
      "name": "BSD",
      "subcategories": [
        {
          "name": "Email Clients",
          "slug": "email-clients"
        },
        {
          "name": "Instant Messaging",
          "slug": "instant-messaging"
        },
        {
          "name": "IRC",
          "slug": "irc"
        }
      ],
      "slug": "bsd"
    },
    {
      "name": "Linux",
      "subcategories": [
        {
          "name": "Email Clients",
          "slug": "email-clients"
        },
        {
          "name": "Instant Messaging",
          "slug": "instant-messaging"
        },
        {
          "name": "IRC",
          "slug": "irc"
        }
      ],
      "slug": "linux"
    },
    {
      "name": "Mac",
      "subcategories": [
        {
          "name": "Email Clients",
          "slug": "email-clients"
        },
        {
          "name": "Instant Messaging",
          "slug": "instant-messaging"
        },
        {
          "name": "IRC",
          "slug": "irc"
        }
      ],
      "slug": "mac"
    },
    {
      "name": "Windows",
      "subcategories": [
        {
          "name": "Email Clients",
          "slug": "email-clients"
        },
        {
          "name": "Instant Messaging",
          "slug": "instant-messaging"
        },
        {
          "name": "IRC",
          "slug": "irc"
        }
      ],
      "slug": "windows"
    }
  ],
  "slug": "mozilla-thunderbird",
  "protocolsSlugged": [
    {
      "name": "GPG",
      "slug": "gpg"
    },
    {
      "name": "IRC",
      "slug": "irc"
    },
    {
      "name": "RSS",
      "slug": "rss"
    },
    {
      "name": "S/MIME",
      "slug": "s-mime"
    },
    {
      "name": "SSL/TLS",
      "slug": "ssl-tls"
    },
    {
      "name": "Tor",
      "slug": "tor"
    },
    {
      "name": "XMPP",
      "slug": "xmpp"
    }
  ]
}