{
  "description": "Metamotore di ricerca che inoltra le tue richieste via proxy ad altri motori di ricerca.",
  "license_url": "",
  "logo": "metager.png",
  "notes": "",
  "privacy_url": "https://www.metager.de/en/privacy.html",
  "source_url": "",
  "name": "MetaGer",
  "tos_url": "",
  "url": "https://metager.de/en/",
  "wikipedia_url": "",
  "protocols": [
    "SSL/TLS"
  ],
  "categories": [
    {
      "name": "Web Services",
      "subcategories": [
        {
          "name": "Web Search",
          "slug": "web-search"
        }
      ],
      "slug": "web-services"
    }
  ],
  "slug": "metager",
  "protocolsSlugged": [
    {
      "name": "SSL/TLS",
      "slug": "ssl-tls"
    }
  ]
}